japanese_sentence_breaker/__init__.py
japanese_sentence_breaker-0.1.0.dist-info/WHEEL
japanese_sentence_breaker-0.1.0.dist-info/METADATA
japanese_sentence_breaker-0.1.0.dist-info/RECORD
