Metadata-Version: 2.1
Name: japanese-sentence-breaker
Version: 0.1.0
Summary: 
Home-page: https://github.com/hpprc/japanese-sentence-breaker
Author: hppRC
Author-email: hpp.ricecake@gmail.com
Requires-Python: >=3.8,<4.0
Classifier: Programming Language :: Python :: 3
Classifier: Programming Language :: Python :: 3.8
Project-URL: Repository, https://github.com/hpprc/japanese-sentence-breaker
